validate_parameters/__init__.py
validate_parameters/base_result.py
validate_parameters/test_base_result.py
validate_parameters/test_validate_param.py
validate_parameters/validate_param.py
validate_parameters-0.1.4.dist-info/LICENSE
validate_parameters-0.1.4.dist-info/METADATA
validate_parameters-0.1.4.dist-info/WHEEL
validate_parameters-0.1.4.dist-info/top_level.txt
validate_parameters-0.1.4.dist-info/zip-safe
validate_parameters-0.1.4.dist-info/RECORD
