Metadata-Version: 2.1
Name: validate-parameters
Version: 0.1.4
Summary: A Python library for checking parameters.
Home-page: http://igit.58corp.com/ops/validate_param.git
Author: chenyang21
Author-email: 745661294@qq.com
License: 58ganji
Platform: UNKNOWN
Classifier: Environment :: Web Environment
Classifier: Intended Audience :: Developers
Classifier: Operating System :: MacOS
Classifier: Operating System :: Microsoft
Classifier: Operating System :: POSIX
Classifier: Operating System :: Unix
Classifier: Topic :: Multimedia :: Video
Classifier: Topic :: Internet
Classifier: Topic :: Software Development :: Libraries :: Python Modules
Classifier: Programming Language :: Python :: 2.6
Classifier: Programming Language :: Python :: 2.7
